{
  "data": [
    {
      "owner": "David Marcu",
      "customClass": "Explore-Swipper-slide-box"
    },
    {
      "owner": "Marko polo",
      "customClass": "Explore-Swipper-slide-box"
    },
    {
      "owner": "Virat Kohli",
      "customClass": "Explore-Swipper-slide-box"
    },
    {
      "owner": "Babar Ajam",
      "customClass": "Explore-Swipper-slide-box"
    },
    {
      "owner": "Shineee Afridi",
      "customClass": "Explore-Swipper-slide-box"
    },
    {
      "owner": "Hayris Rauf",
      "customClass": "Explore-Swipper-slide-box"
    },
    {
      "owner": "Hayris Rauf",
      "customClass": "Explore-Swipper-slide-box"
    },

    {
      "owner": "Krishna Ronaldo",
      "customClass": "Explore-Swipper-slide-box"
    },
    {
      "owner": "Lionel Mausi",
      "customClass": "Explore-Swipper-slide-box"
    },
    {
      "owner": "Talha Ghouri",
      "customClass": "Explore-Swipper-slide-box"
    },
    {
      "owner": "Qaseem Faheem",
      "customClass": "Explore-Swipper-slide-box"
    },
    {
      "owner": "Bilal Ameen",
      "customClass": "Explore-Swipper-slide-box"
    }
  ]
}
